README.rst
setup.py
Tantamount.egg-info/PKG-INFO
Tantamount.egg-info/SOURCES.txt
Tantamount.egg-info/dependency_links.txt
Tantamount.egg-info/requires.txt
Tantamount.egg-info/top_level.txt
example/__init__.py
example/example.py
example/examplestate.py
tantamount/__init__.py
tantamount/astate.py
tantamount/fsm2dot.py
tantamount/machine.py
tantamount/simplestate.py
tests_unit/__init__.py
tests_unit/test_basic.py
tests_unit/test_hook.py
tests_unit/test_longterm.py
tests_unit/test_setup.py
tests_unit/test_simplestate.py