Metadata-Version: 1.2
Name: Tantamount
Version: 0.3.2
Summary: yeT Another fiNite sTate machine with event And tiMeOUt traNsiTions
Home-page: https://gitlab.com/tgd1975/tantamount/
Author: Tobias Gawron-Deutsch
Author-email: tobias@strix.at
License: MIT license
Keywords: fsm finite state machine timeout events
Platform: UNKNOWN
Classifier: Development Status :: 4 - Beta
Classifier: Environment :: Console
Classifier: Environment :: No Input/Output (Daemon)
Classifier: Intended Audience :: Developers
Classifier: Programming Language :: Python :: 3
Classifier: License :: OSI Approved :: MIT License
Requires-Python: >=3.5
